hstore_field
