Metadata-Version: 1.0
Name: hstore-field
Version: 1.0.3
Summary: Support for PostgreSQL's hstore for Django.
Home-page: http://github.com/anantasty/hstore-field
Author: Eric Russell, Anant Asthana
Author-email: eric-r@pobox.com,anant.asty@gmail.com
License: BSD
Platform: UNKNOWN
